{
  "success": true,
  "data": {
    "id": "workspace.dingtalk.com",
    "name": "钉钉·个人版",
    "description": "钉钉推出的个人版办公应用程序，内置AI智能助手，可进行AI创作、AI对话、AI绘画",
    "category": "productivity",
    "company": "",
    "release_date": "2025-07-03",
    "update_date": "2025-07-03",
    "version": "1.0",
    "price": 0,
    "currency": "USD",
    "content_rating": "Everyone",
    "score": 4.5,
    "like_count": null,
    "review_count": null,
    "logo_url": "/icons/tool-icons/钉钉_个人版.png",
    "website_url": "https://workspace.dingtalk.com/welcome",
    "privacy_policy_url": null,
    "video_url": null,
    "size": null,
    "in_app_purchases": false,
    "ad_supported": false,
    "downloads": 0,
    "developer_email": null,
    "subcategory": "general_chatbot,ai_document_tools,ai_image_generation",
    "is_trending": false,
    "tags": null,
    "is_pending": false,
    "screenshot_url": "/images/tools/_______first.png",
    "htmlContent": "{\"functions\":[{\"name\":\"AI创作\",\"description\":\"钉钉·个人版的AI创作功能支持用户快速生成文档、表格、PPT等内容。通过自然语言输入，AI能够自动生成结构化的文档，大幅提升内容创作效率。技术特点包括基于大模型的自然语言处理能力，能够理解用户意图并生成高质量内容。\"},{\"name\":\"AI对话\",\"description\":\"AI对话功能允许用户与智能助手进行自然语言交互，解答问题、提供建议或执行任务。该功能基于先进的对话模型，能够理解上下文并提供精准的回答，适用于日常办公中的信息查询和任务管理。\"},{\"name\":\"AI绘画\",\"description\":\"AI绘画功能支持用户通过文字描述生成图像，适用于创意设计和视觉内容创作。该功能利用生成对抗网络（GAN）技术，能够快速生成高质量的图像，满足用户的多样化需求。\"}],\"roles\":[{\"name\":\"内容创作者\",\"description\":\"内容创作者可以利用钉钉·个人版的AI创作功能快速生成文章、报告或社交媒体内容。通过输入关键词或简要描述，AI能够自动生成初稿，创作者只需进行少量修改即可完成高质量内容。此外，AI绘画功能还能帮助创作者快速生成配图，提升内容吸引力。\"},{\"name\":\"决策汇报者\",\"description\":\"决策汇报者可以使用AI文档工具快速生成PPT和报告，节省大量时间。AI能够根据输入的关键点自动生成结构化内容，并建议合适的图表和排版。汇报者只需专注于核心信息的提炼，AI会处理其余繁琐的文档工作。\"},{\"name\":\"学生\",\"description\":\"学生可以通过AI对话功能获取学习建议、解答疑问或生成学习笔记。AI能够根据课程内容生成摘要和思维导图，帮助学生高效复习。此外，AI创作功能还能辅助完成作业和论文，提升学习效率。\"}],\"features\":[{\"name\":\"智能化办公\",\"description\":\"钉钉·个人版通过AI技术将传统办公流程智能化，大幅提升工作效率。与竞品相比，其优势在于深度整合了钉钉生态的协作功能，用户可以在一个平台上完成多种办公任务，无需切换多个工具。\"},{\"name\":\"多模态AI支持\",\"description\":\"钉钉·个人版不仅支持文本生成，还具备图像生成和语音交互能力，满足用户多样化的需求。这种多模态AI支持使其在办公场景中更具竞争力，能够覆盖更广泛的使用场景。\"}],\"scenarios\":[{\"name\":\"快速生成工作报告\",\"description\":\"用户只需输入报告的主题和关键点，AI会自动生成结构化的报告内容，包括标题、段落和图表建议。用户可以根据需要调整内容，最终生成一份完整的报告，整个过程仅需几分钟。\"},{\"name\":\"创意设计辅助\",\"description\":\"设计师或营销人员可以通过AI绘画功能生成创意图像。输入文字描述后，AI会生成多张候选图像，用户可以选择最符合需求的进行进一步编辑或直接使用，大幅缩短设计周期。\"}],\"pricing_plan\":[{\"name\":\"免费版\",\"description\":\"钉钉·个人版目前提供免费使用，包含基本的AI创作、AI对话和AI绘画功能。免费版可能有使用次数或生成内容的限制，具体限制需参考官网最新信息。\"}],\"usage\":[{\"name\":\"使用AI创作功能\",\"description\":\"1. 打开钉钉·个人版应用；2. 选择AI创作功能；3. 输入内容主题或关键词；4. 等待AI生成初稿；5. 编辑并保存最终文档。\"},{\"name\":\"使用AI对话功能\",\"description\":\"1. 在应用中打开AI对话界面；2. 输入问题或指令；3. 查看AI生成的回答；4. 根据需要进行后续交互。\"}],\"questions\":[{\"name\":\"钉钉·个人版是否收费？\",\"description\":\"目前钉钉·个人版提供免费使用，但可能有部分高级功能或使用次数限制。具体收费情况请参考官网最新公告。\"},{\"name\":\"如何提升AI生成内容的质量？\",\"description\":\"用户可以通过提供更详细的关键词或描述来提升AI生成内容的质量。清晰的输入通常能帮助AI更准确地理解需求，从而生成更符合预期的内容。\"}]}",
    "rolelist": [
      "content_creator",
      "decision_maker",
      "student"
    ],
    "app_store_url": null,
    "github_url": null,
    "stackoverflow_url": null,
    "ranknum": 213,
    "view_count": 0,
    "screenshots": [
      "/images/tools/_______first.png"
    ],
    "subcategory_names": "AI文档工具,AI图像生成,通用聊天机器人",
    "rolenames": "内容创作者,决策汇报者,学生",
    "seo_keywords": [
      "钉钉·个人版",
      "钉钉·个人版 AI工具",
      "钉钉·个人版是什么",
      "钉钉·个人版介绍",
      "通用聊天机器人",
      "通用聊天机器人工具",
      "通用聊天机器人推荐",
      "AI文档工具",
      "AI文档工具工具",
      "AI文档工具推荐",
      "AI图像生成",
      "AI图像生成工具",
      "AI图像生成推荐",
      "免费",
      "免费工具",
      "免费AI工具",
      "零成本",
      "无需付费",
      "钉钉·个人版怎么用",
      "钉钉·个人版功能介绍",
      "钉钉·个人版使用方法",
      "AI工具推荐",
      "人工智能工具",
      "智能工具",
      "效率工具",
      "高评分工具",
      "优质AI工具",
      "推荐工具"
    ],
    "meta_description": "钉钉·个人版是一款免费AI文档工具，钉钉推出的个人版办公应用程序，内置AI智能助手，可进行AI创作、AI对话、AI绘画。适合内容创作者、决策汇报者使用，立即体验这款优秀的AI工具！",
    "seo_title": "钉钉·个人版 - AI文档工具 | AIRankBox",
    "canonical_url": "https://airankbox.com/tools/workspace.dingtalk.com",
    "features": [
      "智能算法优化",
      "用户友好界面",
      "高效处理能力",
      "多平台支持",
      "实时协作功能"
    ],
    "pricing": {
      "free": true,
      "plans": [
        {
          "name": "免费版",
          "price": 0,
          "features": [
            "基础功能",
            "有限使用"
          ]
        },
        {
          "name": "专业版",
          "price": 29,
          "features": [
            "高级功能",
            "无限使用",
            "优先支持"
          ]
        }
      ]
    },
    "similar_tools": [
      {
        "id": "0wai",
        "name": "魔撰写作",
        "description": "出门问问旗下推出的AI智能写作工具",
        "category": "productivity",
        "company": "",
        "release_date": "2025-07-03",
        "update_date": "2025-07-03",
        "version": "1.0",
        "price": 0,
        "currency": "USD",
        "content_rating": "Everyone",
        "score": 4.5,
        "like_count": null,
        "review_count": null,
        "logo_url": "/icons/tool-icons/魔撰写作.png",
        "website_url": "https://www.moyin.com/",
        "privacy_policy_url": null,
        "video_url": null,
        "size": null,
        "in_app_purchases": false,
        "ad_supported": false,
        "downloads": 0,
        "developer_email": null,
        "subcategory": "ai_official_writing,ai_novel_writing,ai_professional_writing",
        "is_trending": false,
        "tags": null,
        "is_pending": false,
        "screenshot_url": "/images/tools/0wai_first.png",
        "rolelist": [
          "content_creator",
          "student",
          "educator"
        ],
        "app_store_url": null,
        "github_url": null,
        "stackoverflow_url": null,
        "ranknum": 307,
        "view_count": 0,
        "screenshots": [
          "/images/tools/0wai_first.png",
          "/images/tools/0wai_scroll.png"
        ],
        "subcategory_names": "AI小说写作,AI公文写作,AI专业写作",
        "rolenames": "内容创作者,学生,教育人士"
      },
      {
        "id": "10sppt.com",
        "name": "秒出PPT",
        "description": "一键生成PPT，智能辅助编辑",
        "category": "productivity",
        "company": "",
        "release_date": "2025-07-03",
        "update_date": "2025-07-03",
        "version": "1.0",
        "price": 0,
        "currency": "USD",
        "content_rating": "Everyone",
        "score": 4.5,
        "like_count": null,
        "review_count": null,
        "logo_url": "/icons/tool-icons/秒出PPT.png",
        "website_url": "https://10sppt.com/pptx/",
        "privacy_policy_url": null,
        "video_url": null,
        "size": null,
        "in_app_purchases": false,
        "ad_supported": false,
        "downloads": 0,
        "developer_email": null,
        "subcategory": "ai_ppt_generation,ai_document_tools",
        "is_trending": false,
        "tags": null,
        "is_pending": false,
        "screenshot_url": "/images/tools/__PPT_first.png",
        "rolelist": [
          "decision_maker",
          "educator",
          "student"
        ],
        "app_store_url": null,
        "github_url": null,
        "stackoverflow_url": null,
        "ranknum": 702,
        "view_count": 0,
        "screenshots": [
          "/images/tools/__PPT_first.png",
          "/images/tools/__PPT_scroll.png"
        ],
        "subcategory_names": "AI文档工具,AI PPT生成",
        "rolenames": "决策汇报者,教育人士,学生"
      },
      {
        "id": "135editor.com",
        "name": "135 AI排版",
        "description": "公众号AI图文排版和智能文案生成工具",
        "category": "productivity",
        "company": "",
        "release_date": "2025-07-03",
        "update_date": "2025-07-03",
        "version": "1.0",
        "price": 0,
        "currency": "USD",
        "content_rating": "Everyone",
        "score": 4.5,
        "like_count": null,
        "review_count": null,
        "logo_url": "/icons/tool-icons/135_AI排版.png",
        "website_url": "https://www.135editor.com/ai_editor/",
        "privacy_policy_url": null,
        "video_url": null,
        "size": null,
        "in_app_purchases": false,
        "ad_supported": false,
        "downloads": 0,
        "developer_email": null,
        "subcategory": "ai_professional_writing,ai_document_tools",
        "is_trending": false,
        "tags": null,
        "is_pending": false,
        "screenshot_url": "/images/tools/135_AI___first.png",
        "rolelist": [
          "content_creator",
          "marketer"
        ],
        "app_store_url": null,
        "github_url": null,
        "stackoverflow_url": null,
        "ranknum": 308,
        "view_count": 0,
        "screenshots": [
          "/images/tools/135_AI___first.png"
        ],
        "subcategory_names": "AI文档工具,AI专业写作",
        "rolenames": "内容创作者,营销人"
      },
      {
        "id": "1f1m",
        "name": "清言PPT",
        "description": "智谱清言联合AiPPT推出的PPT生成智能体",
        "category": "productivity",
        "company": "",
        "release_date": "2025-07-03",
        "update_date": "2025-07-03",
        "version": "1.0",
        "price": 0,
        "currency": "USD",
        "content_rating": "Everyone",
        "score": 4.5,
        "like_count": null,
        "review_count": null,
        "logo_url": "/icons/tool-icons/清言PPT.jpg",
        "website_url": "https://chatglm.cn/main/alltoolsdetail",
        "privacy_policy_url": null,
        "video_url": null,
        "size": null,
        "in_app_purchases": false,
        "ad_supported": false,
        "downloads": 0,
        "developer_email": null,
        "subcategory": "ai_ppt_generation,ai_document_tools",
        "is_trending": false,
        "tags": null,
        "is_pending": false,
        "screenshot_url": "/images/tools/__PPT_first.png",
        "rolelist": [
          "decision_maker",
          "educator",
          "content_creator"
        ],
        "app_store_url": null,
        "github_url": null,
        "stackoverflow_url": null,
        "ranknum": 309,
        "view_count": 0,
        "screenshots": [
          "/images/tools/__PPT_first.png"
        ],
        "subcategory_names": "AI文档工具,AI PPT生成",
        "rolenames": "决策汇报者,教育人士,内容创作者"
      },
      {
        "id": "34sp",
        "name": "文心智能体平台",
        "description": "百度推出的智能体构建平台",
        "category": "productivity",
        "company": "",
        "release_date": "2025-07-03",
        "update_date": "2025-07-03",
        "version": "1.0",
        "price": 0,
        "currency": "USD",
        "content_rating": "Everyone",
        "score": 4.5,
        "like_count": null,
        "review_count": null,
        "logo_url": "/icons/tool-icons/文心智能体平台.png",
        "website_url": "https://agents.baidu.com/",
        "privacy_policy_url": null,
        "video_url": null,
        "size": null,
        "in_app_purchases": false,
        "ad_supported": false,
        "downloads": 0,
        "developer_email": null,
        "subcategory": "ai_dev_platform,general_chatbot,role_playing_chat",
        "is_trending": false,
        "tags": null,
        "is_pending": false,
        "screenshot_url": "/images/tools/________first.png",
        "rolelist": [
          "developer",
          "content_creator",
          "customer_service"
        ],
        "app_store_url": null,
        "github_url": null,
        "stackoverflow_url": null,
        "ranknum": 111,
        "view_count": 0,
        "screenshots": [
          "/images/tools/________first.png"
        ],
        "subcategory_names": "AI开发平台,通用聊天机器人,扮演对话",
        "rolenames": "开发者,内容创作者,客服人员"
      },
      {
        "id": "588tool.com",
        "name": "库宝AI工作助手",
        "description": "千库网推出的多功能AI创作工具",
        "category": "productivity",
        "company": "",
        "release_date": "2025-07-03",
        "update_date": "2025-07-03",
        "version": "1.0",
        "price": 0,
        "currency": "USD",
        "content_rating": "Everyone",
        "score": 4.5,
        "like_count": null,
        "review_count": null,
        "logo_url": "/icons/tool-icons/库宝AI工作助手.png",
        "website_url": "https://588tool.com/",
        "privacy_policy_url": null,
        "video_url": null,
        "size": null,
        "in_app_purchases": false,
        "ad_supported": false,
        "downloads": 0,
        "developer_email": null,
        "subcategory": "ai_image_generation,ai_image_processing",
        "is_trending": false,
        "tags": null,
        "is_pending": false,
        "screenshot_url": "/images/tools/588tool.com_first.png",
        "rolelist": [
          "designer",
          "content_creator",
          "marketer"
        ],
        "app_store_url": null,
        "github_url": null,
        "stackoverflow_url": null,
        "ranknum": 310,
        "view_count": 0,
        "screenshots": [
          "/images/tools/588tool.com_first.png"
        ],
        "subcategory_names": "AI图像生成,AI图像处理",
        "rolenames": "设计师,内容创作者,营销人"
      },
      {
        "id": "58pic.com",
        "name": "千图网",
        "description": "在线设计图片素材平台",
        "category": "productivity",
        "company": "",
        "release_date": "2025-07-03",
        "update_date": "2025-07-03",
        "version": "1.0",
        "price": 0,
        "currency": "USD",
        "content_rating": "Everyone",
        "score": 4.5,
        "like_count": null,
        "review_count": null,
        "logo_url": "/icons/tool-icons/千图网.png",
        "website_url": "https://www.58pic.com/",
        "privacy_policy_url": null,
        "video_url": null,
        "size": null,
        "in_app_purchases": false,
        "ad_supported": false,
        "downloads": 0,
        "developer_email": null,
        "subcategory": "ai_image_generation,ai_image_optimization,ai_ppt_generation",
        "is_trending": false,
        "tags": null,
        "is_pending": false,
        "screenshot_url": "/images/tools/____first.png",
        "rolelist": [
          "designer",
          "content_creator",
          "marketer"
        ],
        "app_store_url": null,
        "github_url": null,
        "stackoverflow_url": null,
        "ranknum": 270,
        "view_count": 0,
        "screenshots": [
          "/images/tools/____first.png",
          "/images/tools/____scroll.png"
        ],
        "subcategory_names": "AI图像生成,AI图片优化修复,AI PPT生成",
        "rolenames": "设计师,内容创作者,营销人"
      },
      {
        "id": "66paper.cn",
        "name": "66AI论文",
        "description": "高质量、低查重、低AIGC率的AI论文写作工具",
        "category": "productivity",
        "company": "",
        "release_date": "2025-07-02",
        "update_date": "2025-07-02",
        "version": "1.0",
        "price": 0,
        "currency": "USD",
        "content_rating": "Everyone",
        "score": 4.5,
        "like_count": null,
        "review_count": null,
        "logo_url": "/icons/tool-icons/66AI论文.png",
        "website_url": "https://www.66paper.cn/AI_A2E1C09",
        "privacy_policy_url": null,
        "video_url": null,
        "size": null,
        "in_app_purchases": false,
        "ad_supported": false,
        "downloads": 0,
        "developer_email": null,
        "subcategory": "ai_paper_writing,academic_research_assistant",
        "is_trending": false,
        "tags": null,
        "is_pending": false,
        "screenshot_url": "/images/tools/66AI___first.png",
        "rolelist": [
          "student",
          "researcher",
          "educator"
        ],
        "app_store_url": null,
        "github_url": null,
        "stackoverflow_url": null,
        "ranknum": 769,
        "view_count": 40,
        "screenshots": [
          "/images/tools/66AI___first.png",
          "/images/tools/66AI___scroll.png"
        ],
        "subcategory_names": "学术研究辅助,AI论文写作",
        "rolenames": "学生,科研人员,教育人士"
      },
      {
        "id": "6l6i",
        "name": "通义万相AI视频",
        "description": "通义万相AI视频是阿里推出的...",
        "category": "productivity",
        "company": "",
        "release_date": "2025-07-02",
        "update_date": "2025-07-02",
        "version": "1.0",
        "price": 0,
        "currency": "USD",
        "content_rating": "Everyone",
        "score": 4.5,
        "like_count": null,
        "review_count": null,
        "logo_url": "/icons/tool-icons/通义万相AI视频.png",
        "website_url": "",
        "privacy_policy_url": null,
        "video_url": null,
        "size": null,
        "in_app_purchases": false,
        "ad_supported": false,
        "downloads": 0,
        "developer_email": null,
        "subcategory": "ai_video_generation,ai_video_editing",
        "is_trending": false,
        "tags": null,
        "is_pending": false,
        "screenshot_url": null,
        "rolelist": [
          "content_creator",
          "marketer",
          "educator"
        ],
        "app_store_url": null,
        "github_url": null,
        "stackoverflow_url": null,
        "ranknum": 311,
        "view_count": 0,
        "screenshots": [],
        "subcategory_names": "AI视频编辑,AI视频生成",
        "rolenames": "内容创作者,营销人,教育人士"
      },
      {
        "id": "73z6",
        "name": "百度作家平台",
        "description": "百度免费AI小说写作工具",
        "category": "productivity",
        "company": "",
        "release_date": "2025-07-03",
        "update_date": "2025-07-03",
        "version": "1.0",
        "price": 0,
        "currency": "USD",
        "content_rating": "Everyone",
        "score": 4.5,
        "like_count": null,
        "review_count": null,
        "logo_url": "/icons/tool-icons/百度作家平台.png",
        "website_url": "https://zuojia.baidu.com",
        "privacy_policy_url": null,
        "video_url": null,
        "size": null,
        "in_app_purchases": false,
        "ad_supported": false,
        "downloads": 0,
        "developer_email": null,
        "subcategory": "ai_novel_writing",
        "is_trending": false,
        "tags": null,
        "is_pending": false,
        "screenshot_url": null,
        "rolelist": [
          "content_creator",
          "student",
          "educator"
        ],
        "app_store_url": null,
        "github_url": null,
        "stackoverflow_url": null,
        "ranknum": 312,
        "view_count": 0,
        "screenshots": [],
        "subcategory_names": "AI小说写作",
        "rolenames": "内容创作者,学生,教育人士"
      }
    ],
    "related_news": [
      {
        "id": 894,
        "title": "AI焦虑的扎克伯格，盯上了华人天才少女",
        "description": "豪门大小姐嫁到的剧情上演？",
        "cover_image": "https://images.tmtpost.com/uploads/images/2025/08/a510a432035e2e16a7c527edddcb7134_1755145073.webp",
        "pub_date": "2025-08-14T04:35",
        "created_at": "2025-08-14 05:04:45",
        "updated_at": "2025-08-14 05:05:41"
      },
      {
        "id": 857,
        "title": "Agent 2025：AI的窄门与宽路",
        "description": "在“AI Agent元年”的光环之下，AI Agent赛道是否只是一场虚假繁荣？",
        "cover_image": "https://images.tmtpost.com/uploads/images/2025/08/471bb516ceab4dc9a9cd44a60536058d_1754975646.jpeg",
        "pub_date": "2025-08-12T05:14",
        "created_at": "2025-08-12 05:52:01",
        "updated_at": "2025-08-14 05:04:12"
      },
      {
        "id": 863,
        "title": "高德地图携手通义实验室，深度共建全球首个AI原生出行智能体",
        "description": "通义大模型的泛化能力与高德在空间场景上的深度积累，在AI原生地图中实现了前所未有的深度融合。",
        "cover_image": "https://images.tmtpost.com/uploads/images/2025/08/22dc42fb53ab451184debe216e88381f_1754973140.png",
        "pub_date": "2025-08-12T04:32",
        "created_at": "2025-08-12 05:52:01",
        "updated_at": "2025-08-14 05:04:25"
      },
      {
        "id": 837,
        "title": "全栈自研硬件，动易科技携摆线关节模组及两款人形机器人亮相2025世界机器人大会",
        "description": "全栈自研硬件，动易科技携摆线关节模组及两款人形机器人亮相2025世界机器人大会",
        "cover_image": null,
        "pub_date": "2025-08-12T02:50",
        "created_at": "2025-08-12 05:52:01",
        "updated_at": "2025-08-14 05:04:42"
      },
      {
        "id": 780,
        "title": "DeepMind刚拿完IMO金牌，科学家就被Meta挖走了，都是华人大牛",
        "description": "这下轮到皮查伊难受了。",
        "cover_image": null,
        "pub_date": "2025-07-23T02:41",
        "created_at": "2025-07-23 06:03:57",
        "updated_at": "2025-07-23 06:24:36"
      },
      {
        "id": 802,
        "title": "Kimi K2官方技术报告出炉：采用384个专家，训练不靠刷题靠“用自己的话再讲一遍”",
        "description": "训练依托于由NVIDIA H800构成的大规模高带宽GPU集群",
        "cover_image": null,
        "pub_date": "2025-07-22T07:14",
        "created_at": "2025-07-23 06:03:57",
        "updated_at": "2025-07-23 06:25:53"
      }
    ]
  },
  "generated_at": "2026-07-16T05:38:42.422Z"
}